configuration_layer/__init__.py
configuration_layer/classes/ConfigurationConsumer.py
configuration_layer/classes/ConfigurationProducer.py
configuration_layer/classes/__init__.py
configuration_layer/configuration/__init__.py
configuration_layer/helpers/__init__.py
configuration_layer/helpers/producer_messages.py
configuration_layer/service_setup/__init__.py
configuration_layer/service_setup/configuration_request.py
configuration_layer/utils/__init__.py
configuration_layer/utils/configuration_validation.py
configuration_layer-1.0.17.dist-info/LICENSE.txt
configuration_layer-1.0.17.dist-info/METADATA
configuration_layer-1.0.17.dist-info/WHEEL
configuration_layer-1.0.17.dist-info/top_level.txt
configuration_layer-1.0.17.dist-info/RECORD
