Metadata-Version: 2.1
Name: configuration-layer
Version: 1.0.17
Summary: client-side service discovery component for microservices.
Home-page: https://github.com/antoniodimariano/client-side-service-discovery-confifguration-lab.git
Author: Antonio Di Mariano
Author-email: antonio.dimariano@gmail.com
License: MIT
Platform: UNKNOWN
Classifier: Development Status :: 4 - Beta
Classifier: Intended Audience :: Developers
Classifier: License :: OSI Approved :: MIT License
Classifier: Programming Language :: Python :: 3.6
Requires-Python: ~=3.6
Requires-Dist: avro-python3
Requires-Dist: confluent-kafka
Requires-Dist: kafka
Requires-Dist: requests
Requires-Dist: microservices-messaging-layer
Requires-Dist: fastavro
